{"stats":{"minecraft:dropped":{"ars_nouveau:worn_notebook":1,"alexsmobs:maggot":1,"minecraft:wheat_seeds":1,"a_man_with_plushies:allay_plush":1,"alexsmobs:animal_dictionary":1,"a_man_with_plushies:wheatley_plush":1,"a_man_with_plushies:sans_plush":3,"regions_unexplored:larch_sapling":13,"culturaldelights:squid":1,"minecraft:blue_carpet":2,"patchouli:guide_book":2,"minecraft:red_carpet":2},"minecraft:killed":{"minecraft:zombie":1},"minecraft:used":{"a_man_with_plushies:wheatley_plush":1,"minecraft:string":1,"minecraft:sugar_cane":3,"regions_unexplored:larch_log":1,"minecraft:red_carpet":2,"a_man_with_plushies:plush_box":1,"alexsmobs:animal_dictionary":1},"minecraft:mined":{"minecraft:red_carpet":2,"regions_unexplored:spruce_shrub":1,"minecraft:ice":1,"treechop:chopped_log":3,"regions_unexplored:frozen_grass":2,"regions_unexplored:larch_leaves":9,"a_man_with_plushies:fact_core_plush":1,"regions_unexplored:medium_grass":1,"minecraft:sugar_cane":2,"minecraft:tripwire":1},"minecraft:picked_up":{"minecraft:stick":11,"simplehats:orange_hat":1,"a_man_with_plushies:allay_plush":1,"minecraft:string":1,"minecraft:blue_carpet":2,"a_man_with_plushies:wheatley_plush":2,"minecraft:red_carpet":4,"a_man_with_plushies:sans_plush":3,"minecraft:wheat_seeds":1,"culturaldelights:squid":1,"regions_unexplored:larch_log":71,"regions_unexplored:larch_sapling":13,"alexsmobs:maggot":1,"minecraft:sugar_cane":3},"minecraft:custom":{"minecraft:time_since_rest":44596,"minecraft:sprint_one_cm":93418,"minecraft:damage_taken":1356,"minecraft:walk_one_cm":66506,"minecraft:mob_kills":1,"minecraft:drop":17,"minecraft:damage_dealt":1119,"minecraft:fly_one_cm":188351,"minecraft:crouch_one_cm":539,"minecraft:play_time":61600,"minecraft:deaths":1,"minecraft:sneak_time":364,"minecraft:damage_dealt_resisted":0,"minecraft:jump":911,"minecraft:leave_game":3,"minecraft:time_since_death":41915,"minecraft:total_world_time":61600,"minecraft:fall_one_cm":31331}},"DataVersion":3465}